IGitt/VERSION
IGitt/__init__.py
IGitt/GitHub/GitHub.py
IGitt/GitHub/GitHubComment.py
IGitt/GitHub/GitHubCommit.py
IGitt/GitHub/GitHubContent.py
IGitt/GitHub/GitHubIssue.py
IGitt/GitHub/GitHubMergeRequest.py
IGitt/GitHub/GitHubNotification.py
IGitt/GitHub/GitHubRepository.py
IGitt/GitHub/GitHubThread.py
IGitt/GitHub/__init__.py
IGitt/GitLab/GitLab.py
IGitt/GitLab/GitLabComment.py
IGitt/GitLab/GitLabCommit.py
IGitt/GitLab/GitLabContent.py
IGitt/GitLab/GitLabIssue.py
IGitt/GitLab/GitLabMergeRequest.py
IGitt/GitLab/GitLabRepository.py
IGitt/GitLab/__init__.py
IGitt/Interfaces/Actions.py
IGitt/Interfaces/Comment.py
IGitt/Interfaces/Commit.py
IGitt/Interfaces/CommitStatus.py
IGitt/Interfaces/Content.py
IGitt/Interfaces/Hoster.py
IGitt/Interfaces/Issue.py
IGitt/Interfaces/MergeRequest.py
IGitt/Interfaces/Notification.py
IGitt/Interfaces/Repository.py
IGitt/Interfaces/Thread.py
IGitt/Interfaces/__init__.py
IGitt/Utils/__init__.py
IGitt-0.4.1.dist-info/DESCRIPTION.rst
IGitt-0.4.1.dist-info/METADATA
IGitt-0.4.1.dist-info/RECORD
IGitt-0.4.1.dist-info/WHEEL
IGitt-0.4.1.dist-info/metadata.json
IGitt-0.4.1.dist-info/top_level.txt
