Metadata-Version: 2.0
Name: IGitt
Version: 0.4.1
Summary: A git(hub/lab/...) hosting abstraction library.
Home-page: UNKNOWN
Author: Lasse Schuirmann
Author-email: lasse.schuirmann@gmail.com
License: MIT
Platform: UNKNOWN
Requires-Dist: GitPython (==1.0.1)
Requires-Dist: requests
